phenaki_pytorch/__init__.py
phenaki_pytorch/attention.py
phenaki_pytorch/cvivit.py
phenaki_pytorch/cvivit_trainer.py
phenaki_pytorch/data.py
phenaki_pytorch/optimizer.py
phenaki_pytorch/phenaki_pytorch.py
phenaki_pytorch/phenaki_trainer.py
phenaki_pytorch/t5.py
phenaki_pytorch-0.5.0.dist-info/LICENSE
phenaki_pytorch-0.5.0.dist-info/METADATA
phenaki_pytorch-0.5.0.dist-info/WHEEL
phenaki_pytorch-0.5.0.dist-info/top_level.txt
phenaki_pytorch-0.5.0.dist-info/RECORD
